{
	"config": {
		"name": "DogHouse8",
		"boxes": [
			{
				"name": "Box 1",
				"dimensions": {
					"width": 100,
					"length": 100,
					"height": 50
				},
				"pickLocation": {
					"x": 0,
					"y": 0,
					"z": 0
				}
			}
		],
		"pallets": [
			{
				"name": "Pallet 1",
				"corner1": {
					"x": 0,
					"y": 100,
					"z": 0
				},
				"corner2": {
					"x": 0,
					"y": 0,
					"z": 0
				},
				"corner3": {
					"x": 100,
					"y": 0,
					"z": 0
				},
				"Layers": [
					{
						"name": "Layer 1",
						"boxPositions": [
							{
								"box": {
									"name": "Box 1",
									"dimensions": {
										"width": 100,
										"length": 100,
										"height": 50
									},
									"pickLocation": {
										"x": 0,
										"y": 0,
										"z": 0
									}
								},
								"position": {
									"x": 0.005192307692307692,
									"y": 0.014567307692307692
								}
							}
						],
						"height": 50
					}
				],
				"Stack": [
					0
				]
			}
		]
	},
	"boxCoordinates": [
		{
			"pickLocation": {
				"x": 0,
				"y": 0,
				"z": 0
			},
			"dropLocation": {
				"x": 50.52,
				"y": 48.54,
				"z": 50
			}
		}
	]
}